palabras/__init__.py
palabras/__main__.py
palabras/cli.py
palabras/core.py
palabras/utils.py
palabras-0.4.2.dist-info/entry_points.txt
palabras-0.4.2.dist-info/LICENSE
palabras-0.4.2.dist-info/WHEEL
palabras-0.4.2.dist-info/METADATA
palabras-0.4.2.dist-info/RECORD
