Metadata-Version: 2.1
Name: palabras
Version: 0.4.2
Summary: (WIP) Look up Spanish words on Wiktionary
Author-email: Paavo Pere <paavo@pere.fi>
Requires-Python: >=3.8
Classifier: License :: OSI Approved :: MIT License
Requires-Dist: beautifulsoup4
Requires-Dist: requests
Requires-Dist: rich
Requires-Dist: pytest ; extra == "test"
Requires-Dist: pytest-cov ; extra == "test"
Requires-Dist: pytest-mock ; extra == "test"
Requires-Dist: mypy ; extra == "test"
Requires-Dist: types-requests ; extra == "test"
Requires-Dist: flake8 ; extra == "test"
Project-URL: Home, https://github.com/paavopere/palabras
Provides-Extra: test
